LICENSE
README.rst
setup.py
docs/HISTORY.txt
docs/readme.txt
js/__init__.py
js.markdown_converter.egg-info/PKG-INFO
js.markdown_converter.egg-info/SOURCES.txt
js.markdown_converter.egg-info/dependency_links.txt
js.markdown_converter.egg-info/entry_points.txt
js.markdown_converter.egg-info/namespace_packages.txt
js.markdown_converter.egg-info/not-zip-safe
js.markdown_converter.egg-info/requires.txt
js.markdown_converter.egg-info/top_level.txt
js/markdown_converter/__init__.py
js/markdown_converter/release.py
js/markdown_converter/resources/Markdown.Converter.js
js/markdown_converter/resources/Markdown.Converter.min.js