Metadata-Version: 1.1
Name: js.markdown-converter
Version: 0.1.0
Summary: Fanstatic resource definition for Markdown.Converter
Home-page: http://www.merchise.org
Author: Merchise Autrement
Author-email: UNKNOWN
License: GPL 3+
Keywords: f,a,n,s,t,a,t,i,c, ,m,a,r,k,d,o,w,n,-,c,o,n,v,e,r,t,e,r, ,r,e,s,o,u,r,c,e
Platform: UNKNOWN
Classifier: Programming Language :: Python
